bblocks/__init__.py
bblocks-2.1.0.dist-info/LICENSE
bblocks-2.1.0.dist-info/METADATA
bblocks-2.1.0.dist-info/WHEEL
bblocks-2.1.0.dist-info/RECORD
