Metadata-Version: 2.3
Name: bblocks
Version: 2.1.0
Summary: Building blocks for development data.
License: MIT
Author: ONE Campaign
Requires-Python: >=3.11,<4.0
Classifier: License :: OSI Approved :: MIT License
Classifier: Programming Language :: Python :: 3
Classifier: Programming Language :: Python :: 3.11
Classifier: Programming Language :: Python :: 3.12
Classifier: Programming Language :: Python :: 3.13
Provides-Extra: all
Provides-Extra: data-importers
Provides-Extra: datacommons-tools
Provides-Extra: places
Requires-Dist: bblocks-data-importers (>=0.4.0,<0.5.0) ; extra == "all"
Requires-Dist: bblocks-data-importers (>=0.4.0,<0.5.0) ; extra == "data-importers"
Requires-Dist: bblocks-datacommons-tools (>=0.0.2,<0.1.0) ; extra == "all"
Requires-Dist: bblocks-datacommons-tools (>=0.0.2,<0.1.0) ; extra == "datacommons-tools"
Requires-Dist: bblocks-places (>=0.0.2,<0.1.0) ; extra == "all"
Requires-Dist: bblocks-places (>=0.0.2,<0.1.0) ; extra == "places"
Project-URL: Documentation, https://docs.one.org/tools/bblocks/
Project-URL: Homepage, https://docs.one.org/tools/bblocks/
Project-URL: Repository, https://github.com/ONEcampaign/bblocks
